{"infos_partie":{"nbjoueurs":1,"pseudo_j1":"","pseudo_j2":"GY","tour":"j1"},"joueur1":{"boat2":{"1":{"x":"3","y":"4"},"2":{"x":"3","y":"4"}},"boat3a":{"1":{"x":"3","y":"4"},"2":{"x":"3","y":"4"},"3":{"x":"3","y":"4"}},"boat3b":{"1":{"x":"3","y":"4"},"2":{"x":"3","y":"4"},"3":{"x":"3","y":"4"}},"boat4":{"1":{"x":"3","y":"4"},"2":{"x":"3","y":"4"},"3":{"x":"3","y":"4"},"4":{"x":"3","y":"4"}},"boat5":{"1":{"x":"3","y":"4"},"2":{"x":"3","y":"4"},"3":{"x":"3","y":"4"},"4":{"x":"3","y":"4"},"5":{"x":"3","y":"4"}}},"joueur2":{"boat2":{"1":{"x":"3","y":"4"},"2":{"x":"3","y":"4"}},"boat3a":{"1":{"x":"3","y":"4"},"2":{"x":"3","y":"4"},"3":{"x":"3","y":"4"}},"boat3b":{"1":{"x":"3","y":"4"},"2":{"x":"3","y":"4"},"3":{"x":"3","y":"4"}},"boat4":{"1":{"x":"3","y":"4"},"2":{"x":"3","y":"4"},"3":{"x":"3","y":"4"},"4":{"x":"3","y":"4"}},"boat5":{"1":{"x":"3","y":"4"},"2":{"x":"3","y":"4"},"3":{"x":"3","y":"4"},"4":{"x":"3","y":"4"},"5":{"x":"3","y":"4"}}}}